{
  "$schema": "https://unpkg.com/knip@5/schema.json",
  "entry": [
    "src/index.ts",
    "src/services/billing-commands/payment.ts",
    "src/services/night-audit-runner.ts"
  ],
  "project": [
    "src/**/*.ts"
  ],
  "ignore": [
    "src/utils/money.ts"
  ],
  "ignoreDependencies": [
    "@tartware/schemas",
    "@tartware/telemetry",
    "@tartware/openapi",
    "@tartware/config",
    "@tartware/tenant-auth",
    "@tartware/command-consumer-utils",
    "@fastify/cors",
    "@fastify/helmet",
    "@fastify/sensible",
    "@tartware/fastify-server"
  ],
  "ignoreBinaries": [
    "swc"
  ]
}
